MANIFEST.in
README.rst
setup.py
docs/HISTORY.txt
openapp_indivo/__init__.py
openapp_indivo/demographics/__init__.py
openapp_indivo/demographics/forms.py
openapp_indivo/demographics/middleware.py
openapp_indivo/demographics/models.py
openapp_indivo/demographics/settings.py
openapp_indivo/demographics/urls.py
openapp_indivo/demographics/utils.py
openapp_indivo/demographics/views.py
openapp_indivo/demographics/registered_apps/user/openapp_indivo.demographics/credentials.json
openapp_indivo/demographics/registered_apps/user/openapp_indivo.demographics/manifest.json
openapp_indivo/demographics/static/openapp_indivo/demographics/images/demographics.png
openapp_indivo/demographics/static/openapp_indivo/demographics/images/demographics.png.copyright
openapp_indivo/demographics/templates/openapp_indivo/demographics/demographics.html
openapp_indivo/demographics/templates/openapp_indivo/demographics/edit.html
openapp_indivo_demographics.egg-info/PKG-INFO
openapp_indivo_demographics.egg-info/SOURCES.txt
openapp_indivo_demographics.egg-info/dependency_links.txt
openapp_indivo_demographics.egg-info/entry_points.txt
openapp_indivo_demographics.egg-info/namespace_packages.txt
openapp_indivo_demographics.egg-info/not-zip-safe
openapp_indivo_demographics.egg-info/requires.txt
openapp_indivo_demographics.egg-info/top_level.txt