Metadata-Version: 1.0
Name: openapp-indivo-demographics
Version: 1.0.1
Summary: App to display and edit the Indivo Demographics Record
Home-page: http://www.openapp.ie
Author: Kevin Gill (OpenApp)
Author-email: kevin.gill@openapp.ie
License: AGPL
Keywords: indivo
Platform: UNKNOWN
Classifier: Programming Language :: Python
Classifier: Topic :: Software Development :: Libraries :: Python Modules
